mlfarm/__init__.py
mlfarm/core.py
mlfarm/debug.py
mlfarm-0.1.2.dist-info/LICENSE
mlfarm-0.1.2.dist-info/METADATA
mlfarm-0.1.2.dist-info/WHEEL
mlfarm-0.1.2.dist-info/top_level.txt
mlfarm-0.1.2.dist-info/RECORD
