Metadata-Version: 2.1
Name: mlfarm
Version: 0.1.2
Summary: Tools for fast development of Machine Learning projects.
Home-page: https://github.com/Oodapow/mlfarm/tree/release
Author: Alexandru Petre
Author-email: petre.v.alexandru@gmail.com
License: UNKNOWN
Platform: UNKNOWN
Classifier: Programming Language :: Python :: 3
Classifier: License :: OSI Approved :: MIT License
Classifier: Operating System :: OS Independent
Requires-Python: >=3.6
